redis_kits/__init__.py
redis_kits/crud_locker.py
redis_kits-0.0.3.dist-info/DESCRIPTION.rst
redis_kits-0.0.3.dist-info/METADATA
redis_kits-0.0.3.dist-info/RECORD
redis_kits-0.0.3.dist-info/WHEEL
redis_kits-0.0.3.dist-info/metadata.json
redis_kits-0.0.3.dist-info/top_level.txt
