Metadata-Version: 2.0
Name: redis-kits
Version: 0.0.3
Summary: Toolkits built upon Redis
Home-page: https://github.com/claydodo/redis_kits
Author: claydodo and his little friends (xiao huo ban)
Author-email: claydodo@foxmail.com
License: UNKNOWN
Platform: UNKNOWN
Classifier: Programming Language :: Python :: 2.7 
Classifier: Programming Language :: Python :: 3 
Classifier: Operating System :: OS Independent
Requires-Dist: redis (>=3)
